[
  {
    "name": "Basalt Island",
    "always_allow_chest_manipulation": true,
    "color": "#007bff",
    "chest_opened_img": "images/boxes/treasure_chest_open.png",
    "chest_unopened_img": "images/boxes/treasure_chest_closed.png",
    "access_rules": [
      "boss_dweller_strife"
    ],
    "children": [
      {
        "name": "Kiln Mountain",
        "sections": [
          {
            "name": "Geyser Climb",
            "item_count": 1
          },
          {
            "name": "Boulder Bowling 1",
            "item_count": 1,
            "chest_unopened_img": "images/boxes/conch_chest_closed.png",
            "chest_opened_img": "images/boxes/conch_chest_open.png"
          },
          {
            "name": "Boulder Bowling 2",
            "item_count": 1
          },
          {
            "name": "Hole in the Wall",
            "item_count": 1
          },
          {
            "name": "Toadcano",
            "hosted_item": "boss_toadcano"
          }
        ],
        "map_locations": [
          {
            "map": "homeworld",
            "x": 672,
            "y": 170,
            "size": 20
          }
        ]
      }
    ]
  }
]