[
  {
    "name": "Recipe: Barbapapa",
    "type": "toggle",
    "img": "images/items/recipe_basicsalad.png",
    "codes": "recipe_barbapapa"
  },
  {
    "name": "Recipe: Milkshake",
    "type": "toggle",
    "img": "images/items/recipe_basicsalad.png",
    "codes": "recipe_milkshake"
  },
  {
    "name": "Recipe: Caramel Corn",
    "type": "toggle",
    "img": "images/items/recipe_basicsalad.png",
    "codes": "recipe_caramelcorn"
  },
  {
    "name": "Recipe: Ice Cream",
    "type": "toggle",
    "img": "images/items/recipe_basicsalad.png",
    "codes": "recipe_icecream"
  },
  {
    "name": "Recipe: Popcorn",
    "type": "toggle",
    "img": "images/items/recipe_basicsalad.png",
    "codes": "recipe_popcorn"
  }
]